[
    {
        "Ticker": "HCP",
        "Security Name": "HashiCorp, Inc.",
        "Closing Price": 33.9,
        "Volume": 2194545,
        "360-Day Mean IV": null,
        "Industry": "Software - Infrastructure",
        "Sector": "Technology",
        "30-Day Call IV": 7.84,
        "30-Day Put IV": 42.63,
        "Market Cap": 6815372514
    },
    {
        "Ticker": "JNPR",
        "Security Name": "Juniper Networks, Inc.",
        "Closing Price": 39.02,
        "Volume": 2918387,
        "360-Day Mean IV": null,
        "Industry": "Communication Equipment",
        "Sector": "Technology",
        "30-Day Call IV": 8.26,
        "30-Day Put IV": null,
        "Market Cap": 12681027740
    },
    {
        "Ticker": "B",
        "Security Name": "Barnes Group, Inc.",
        "Closing Price": 46.78,
        "Volume": 803619,
        "360-Day Mean IV": null,
        "Industry": "Specialty Industrial Machinery",
        "Sector": "Industrials",
        "30-Day Call IV": 10.77,
        "30-Day Put IV": 14.93,
        "Market Cap": 2371842928
    },
    {
        "Ticker": "EDR",
        "Security Name": "Endeavor Group Holdings, Inc.",
        "Closing Price": 29.13,
        "Volume": 1614821,
        "360-Day Mean IV": null,
        "Industry": "Entertainment",
        "Sector": "Communication Services",
        "30-Day Call IV": 13.62,
        "30-Day Put IV": 38.59,
        "Market Cap": 8810692658
    },
    {
        "Ticker": "ZUO",
        "Security Name": "Zuora, Inc.",
        "Closing Price": 9.88,
        "Volume": 1869872,
        "360-Day Mean IV": null,
        "Industry": "Software - Infrastructure",
        "Sector": "Technology",
        "30-Day Call IV": 15.5,
        "30-Day Put IV": 28.54,
        "Market Cap": 1463228000
    },
    {
        "Ticker": "BXSL",
        "Security Name": "Blackstone Secured Lending Fund",
        "Closing Price": 31.49,
        "Volume": 650639,
        "360-Day Mean IV": null,
        "Industry": "Asset Management",
        "Sector": "Financial Services",
        "30-Day Call IV": 18.73,
        "30-Day Put IV": 29.2,
        "Market Cap": 6059905590
    },
    {
        "Ticker": "GBDC",
        "Security Name": "Golub Capital BDC, Inc.",
        "Closing Price": 15.51,
        "Volume": 1164175,
        "360-Day Mean IV": null,
        "Industry": "Asset Management",
        "Sector": "Financial Services",
        "30-Day Call IV": 19.61,
        "30-Day Put IV": null,
        "Market Cap": 2660233431
    },
    {
        "Ticker": "KDP",
        "Security Name": "Keurig Dr Pepper, Inc",
        "Closing Price": 33.86,
        "Volume": 11117059,
        "360-Day Mean IV": null,
        "Industry": "Beverages - Non-Alcoholic",
        "Sector": "Consumer Defensive",
        "30-Day Call IV": 20.29,
        "30-Day Put IV": 20.27,
        "Market Cap": 45917084725
    },
    {
        "Ticker": "HLN",
        "Security Name": "Haleon PLC Sponsored ADR",
        "Closing Price": 9.98,
        "Volume": 5228097,
        "360-Day Mean IV": null,
        "Industry": "Drug Manufacturers - Specialty & Generic",
        "Sector": "Healthcare",
        "30-Day Call IV": 21.01,
        "30-Day Put IV": 20.92,
        "Market Cap": 46080523416
    },
    {
        "Ticker": "AGNC",
        "Security Name": "AGNC Investment Corp.",
        "Closing Price": 9.64,
        "Volume": 52102487,
        "360-Day Mean IV": null,
        "Industry": "REIT - Mortgage",
        "Sector": "Real Estate",
        "30-Day Call IV": 21.73,
        "30-Day Put IV": 21.62,
        "Market Cap": 7007597651
    },
    {
        "Ticker": "BXMT",
        "Security Name": "Blackstone Mortgage Trust, Inc.",
        "Closing Price": 18.56,
        "Volume": 1232814,
        "360-Day Mean IV": null,
        "Industry": "REIT - Mortgage",
        "Sector": "Real Estate",
        "30-Day Call IV": 28.23,
        "30-Day Put IV": 29.11,
        "Market Cap": 3222405388
    },
    {
        "Ticker": "MMM",
        "Security Name": "3M Company",
        "Closing Price": 130.29,
        "Volume": 5218571,
        "360-Day Mean IV": null,
        "Industry": "Conglomerates",
        "Sector": "Industrials",
        "30-Day Call IV": 28.23,
        "30-Day Put IV": 21.78,
        "Market Cap": 71575283280
    },
    {
        "Ticker": "GE",
        "Security Name": "GE Aerospace",
        "Closing Price": 175.36,
        "Volume": 5564666,
        "360-Day Mean IV": null,
        "Industry": "Specialty Industrial Machinery",
        "Sector": "Industrials",
        "30-Day Call IV": 28.69,
        "30-Day Put IV": 28.77,
        "Market Cap": 190144779765
    },
    {
        "Ticker": "PSEC",
        "Security Name": "Prospect Capital Corporation",
        "Closing Price": 5.33,
        "Volume": 1887142,
        "360-Day Mean IV": null,
        "Industry": "Asset Management",
        "Sector": "Financial Services",
        "30-Day Call IV": 28.72,
        "30-Day Put IV": 42.86,
        "Market Cap": 2226648482
    },
    {
        "Ticker": "ALTM",
        "Security Name": "Arcadium Lithium PLC",
        "Closing Price": 5.48,
        "Volume": 11029703,
        "360-Day Mean IV": null,
        "Industry": "Specialty Chemicals",
        "Sector": "Basic Materials",
        "30-Day Call IV": 29.88,
        "30-Day Put IV": 33.04,
        "Market Cap": 5892050214
    },
    {
        "Ticker": "INFN",
        "Security Name": "Infinera Corporation",
        "Closing Price": 6.74,
        "Volume": 536233,
        "360-Day Mean IV": null,
        "Industry": "Communication Equipment",
        "Sector": "Technology",
        "30-Day Call IV": 33.45,
        "30-Day Put IV": 161.28,
        "Market Cap": 1579114364
    },
    {
        "Ticker": "ARR",
        "Security Name": "ARMOUR Residential REIT, Inc.",
        "Closing Price": 19.1,
        "Volume": 3033184,
        "360-Day Mean IV": null,
        "Industry": "REIT - Mortgage",
        "Sector": "Real Estate",
        "30-Day Call IV": 33.98,
        "30-Day Put IV": null,
        "Market Cap": 931422367
    },
    {
        "Ticker": "NWBI",
        "Security Name": "Northwest Bancshares, Inc.",
        "Closing Price": 13.48,
        "Volume": 459756,
        "360-Day Mean IV": null,
        "Industry": "Banks - Regional",
        "Sector": "Financial Services",
        "30-Day Call IV": 41.04,
        "30-Day Put IV": null,
        "Market Cap": 1715520000
    },
    {
        "Ticker": "AQN",
        "Security Name": "Algonquin Power & Utilities Corp.",
        "Closing Price": 5.01,
        "Volume": 2373788,
        "360-Day Mean IV": null,
        "Industry": "Utilities - Renewable",
        "Sector": "Utilities",
        "30-Day Call IV": 41.93,
        "30-Day Put IV": 39.97,
        "Market Cap": 3455080723
    },
    {
        "Ticker": "TAK",
        "Security Name": "Takeda Pharmaceutical Co.",
        "Closing Price": 13.6,
        "Volume": 1889391,
        "360-Day Mean IV": null,
        "Industry": "Drug Manufacturers - Specialty & Generic",
        "Sector": "Healthcare",
        "30-Day Call IV": 45.36,
        "30-Day Put IV": 30.28,
        "Market Cap": 42677166220
    },
    {
        "Ticker": "PDM",
        "Security Name": "Piedmont Office Realty Trust, Inc.",
        "Closing Price": 10.09,
        "Volume": 1042859,
        "360-Day Mean IV": null,
        "Industry": "REIT - Office",
        "Sector": "Real Estate",
        "30-Day Call IV": 45.48,
        "30-Day Put IV": null,
        "Market Cap": 1251159475
    },
    {
        "Ticker": "PK",
        "Security Name": "Park Hotels & Resorts Inc.",
        "Closing Price": 13.96,
        "Volume": 2673525,
        "360-Day Mean IV": null,
        "Industry": "REIT - Hotel & Motel",
        "Sector": "Real Estate",
        "30-Day Call IV": 46.62,
        "30-Day Put IV": 62.02,
        "Market Cap": 2939941895
    },
    {
        "Ticker": "WTTR",
        "Security Name": "Select Water Solutions, Inc.",
        "Closing Price": 10.79,
        "Volume": 627688,
        "360-Day Mean IV": null,
        "Industry": "Specialty Chemicals",
        "Sector": "Basic Materials",
        "30-Day Call IV": 50.13,
        "30-Day Put IV": 73.49,
        "Market Cap": 1283100100
    },
    {
        "Ticker": "INST",
        "Security Name": "Instructure Holdings, Inc.",
        "Closing Price": 23.53,
        "Volume": 692140,
        "360-Day Mean IV": null,
        "Industry": "Software - Application",
        "Sector": "Technology",
        "30-Day Call IV": 50.41,
        "30-Day Put IV": 45.32,
        "Market Cap": 3433682616
    },
    {
        "Ticker": "RLJ",
        "Security Name": "RLJ Lodging Trust",
        "Closing Price": 9.07,
        "Volume": 1467942,
        "360-Day Mean IV": null,
        "Industry": "REIT - Hotel & Motel",
        "Sector": "Real Estate",
        "30-Day Call IV": 50.78,
        "30-Day Put IV": null,
        "Market Cap": 1414018460
    },
    {
        "Ticker": "INTR",
        "Security Name": "Inter & Co. Inc.",
        "Closing Price": 6.61,
        "Volume": 1545204,
        "360-Day Mean IV": null,
        "Industry": "Banks - Regional",
        "Sector": "Financial Services",
        "30-Day Call IV": 50.98,
        "30-Day Put IV": 111.89,
        "Market Cap": 2658479469
    },
    {
        "Ticker": "AMD",
        "Security Name": "Advanced Micro Devices, Inc.",
        "Closing Price": 159.92,
        "Volume": 29503093,
        "360-Day Mean IV": null,
        "Industry": "Semiconductors",
        "Sector": "Technology",
        "30-Day Call IV": 54.9,
        "30-Day Put IV": 54.71,
        "Market Cap": 258480914250
    },
    {
        "Ticker": "DNB",
        "Security Name": "Dun & Bradstreet Holdings, Inc.",
        "Closing Price": 10.86,
        "Volume": 1485731,
        "360-Day Mean IV": null,
        "Industry": "Financial Data & Stock Exchanges",
        "Sector": "Financial Services",
        "30-Day Call IV": 55.67,
        "30-Day Put IV": null,
        "Market Cap": 4807912180
    },
    {
        "Ticker": "WOW",
        "Security Name": "WideOpenWest, Inc.",
        "Closing Price": 5.17,
        "Volume": 271191,
        "360-Day Mean IV": null,
        "Industry": "Telecom Services",
        "Sector": "Communication Services",
        "30-Day Call IV": 56.73,
        "30-Day Put IV": null,
        "Market Cap": 437210697
    },
    {
        "Ticker": "IAS",
        "Security Name": "Integral Ad Science Holding Corp.",
        "Closing Price": 11.88,
        "Volume": 1566070,
        "360-Day Mean IV": null,
        "Industry": "Advertising Agencies",
        "Sector": "Communication Services",
        "30-Day Call IV": 63.5,
        "30-Day Put IV": 72.49,
        "Market Cap": 1907256839
    },
    {
        "Ticker": "RCM",
        "Security Name": "R1 RCM Inc.",
        "Closing Price": 14.25,
        "Volume": 1799707,
        "360-Day Mean IV": null,
        "Industry": "Health Information Services",
        "Sector": "Healthcare",
        "30-Day Call IV": 63.97,
        "30-Day Put IV": 28.13,
        "Market Cap": 6002887027
    },
    {
        "Ticker": "SITC",
        "Security Name": "SITE CENTERS CORP.",
        "Closing Price": 16.82,
        "Volume": 1690180,
        "360-Day Mean IV": null,
        "Industry": "REIT - Retail",
        "Sector": "Real Estate",
        "30-Day Call IV": 72.24,
        "30-Day Put IV": 76.1,
        "Market Cap": 881128752
    },
    {
        "Ticker": "BRKL",
        "Security Name": "Brookline Bancorp, Inc.",
        "Closing Price": 11.26,
        "Volume": 482552,
        "360-Day Mean IV": null,
        "Industry": "Banks - Regional",
        "Sector": "Financial Services",
        "30-Day Call IV": 76.6,
        "30-Day Put IV": null,
        "Market Cap": 1000952937
    },
    {
        "Ticker": "AVXL",
        "Security Name": "Anavex Life Sciences Corp.",
        "Closing Price": 5.78,
        "Volume": 690917,
        "360-Day Mean IV": null,
        "Industry": "Biotechnology",
        "Sector": "Healthcare",
        "30-Day Call IV": 83.33,
        "30-Day Put IV": 54.83,
        "Market Cap": 489228083
    },
    {
        "Ticker": "RILY",
        "Security Name": "B. Riley Financial, Inc.",
        "Closing Price": 5.63,
        "Volume": 1912676,
        "360-Day Mean IV": null,
        "Industry": "Financial Conglomerates",
        "Sector": "Financial Services",
        "30-Day Call IV": 183.09,
        "30-Day Put IV": null,
        "Market Cap": 172181563
    },
    {
        "Ticker": "RZLT",
        "Security Name": "Rezolute, Inc.",
        "Closing Price": 5.63,
        "Volume": 312172,
        "360-Day Mean IV": null,
        "Industry": "Biotechnology",
        "Sector": "Healthcare",
        "30-Day Call IV": 199.64,
        "30-Day Put IV": 122.5,
        "Market Cap": 225960877
    },
    {
        "Ticker": "K",
        "Security Name": "Kellanova",
        "Closing Price": 80.6,
        "Volume": 2466403,
        "360-Day Mean IV": 7.27,
        "Industry": "Packaged Foods",
        "Sector": "Consumer Defensive",
        "30-Day Call IV": 17.02,
        "30-Day Put IV": 9.88,
        "Market Cap": 27555821786
    },
    {
        "Ticker": "VSTO",
        "Security Name": "Vista Outdoor Inc.",
        "Closing Price": 43.91,
        "Volume": 580012,
        "360-Day Mean IV": 10.34,
        "Industry": "Leisure",
        "Sector": "Consumer Cyclical",
        "30-Day Call IV": 19.71,
        "30-Day Put IV": 24.36,
        "Market Cap": 2561533540
    },
    {
        "Ticker": "STER",
        "Security Name": "Sterling Check Corp.",
        "Closing Price": 16.79,
        "Volume": 66101,
        "360-Day Mean IV": 12.51,
        "Industry": "Software - Application",
        "Sector": "Technology",
        "30-Day Call IV": 45.15,
        "30-Day Put IV": null,
        "Market Cap": 1641245720
    },
    {
        "Ticker": "OBDC",
        "Security Name": "Blue Owl Capital Corporation",
        "Closing Price": 15.31,
        "Volume": 1105168,
        "360-Day Mean IV": 12.78,
        "Industry": "Credit Services",
        "Sector": "Financial Services",
        "30-Day Call IV": 25.73,
        "30-Day Put IV": 22.13,
        "Market Cap": 5966810209
    },
    {
        "Ticker": "ARCC",
        "Security Name": "Ares Capital Corporation",
        "Closing Price": 21.67,
        "Volume": 1883853,
        "360-Day Mean IV": 12.91,
        "Industry": "Asset Management",
        "Sector": "Financial Services",
        "30-Day Call IV": 16.62,
        "30-Day Put IV": 16.72,
        "Market Cap": 13170236215
    },
    {
        "Ticker": "CTLT",
        "Security Name": "Catalent, Inc.",
        "Closing Price": 58.81,
        "Volume": 1322443,
        "360-Day Mean IV": 13.47,
        "Industry": "Drug Manufacturers - Specialty & Generic",
        "Sector": "Healthcare",
        "30-Day Call IV": 21.54,
        "30-Day Put IV": 19.59,
        "Market Cap": 10643424919
    },
    {
        "Ticker": "FSK",
        "Security Name": "FS KKR Capital Corp.",
        "Closing Price": 20.73,
        "Volume": 771833,
        "360-Day Mean IV": 15.09,
        "Industry": "Asset Management",
        "Sector": "Financial Services",
        "30-Day Call IV": 24.76,
        "30-Day Put IV": 28.54,
        "Market Cap": 5805777156
    },
    {
        "Ticker": "MPLX",
        "Security Name": "MPLX LP",
        "Closing Price": 43.77,
        "Volume": 1252845,
        "360-Day Mean IV": 15.37,
        "Industry": "Oil & Gas Midstream",
        "Sector": "Energy",
        "30-Day Call IV": 20.28,
        "30-Day Put IV": 15.81,
        "Market Cap": 44478885570
    },
    {
        "Ticker": "EPD",
        "Security Name": "Enterprise Products Partners L.P.",
        "Closing Price": 29.14,
        "Volume": 3669757,
        "360-Day Mean IV": 15.85,
        "Industry": "Oil & Gas Midstream",
        "Sector": "Energy",
        "30-Day Call IV": 8.52,
        "30-Day Put IV": 21.89,
        "Market Cap": 63279210435
    },
    {
        "Ticker": "ATO",
        "Security Name": "Atmos Energy Corporation",
        "Closing Price": 141.49,
        "Volume": 590059,
        "360-Day Mean IV": 15.97,
        "Industry": "Utilities - Regulated Gas",
        "Sector": "Utilities",
        "30-Day Call IV": 20.8,
        "30-Day Put IV": 17.49,
        "Market Cap": 21347594653
    },
    {
        "Ticker": "OGE",
        "Security Name": "OGE Energy Corporation",
        "Closing Price": 40.65,
        "Volume": 810141,
        "360-Day Mean IV": 16.08,
        "Industry": "Utilities - Regulated Electric",
        "Sector": "Utilities",
        "30-Day Call IV": 39.46,
        "30-Day Put IV": null,
        "Market Cap": 8152269777
    },
    {
        "Ticker": "CMS",
        "Security Name": "CMS Energy Corporation",
        "Closing Price": 71.16,
        "Volume": 1271488,
        "360-Day Mean IV": 16.18,
        "Industry": "Utilities - Regulated Electric",
        "Sector": "Utilities",
        "30-Day Call IV": 17.74,
        "30-Day Put IV": null,
        "Market Cap": 21250897056
    },
    {
        "Ticker": "HTGC",
        "Security Name": "Hercules Capital, Inc.",
        "Closing Price": 20.14,
        "Volume": 1005575,
        "360-Day Mean IV": 16.22,
        "Industry": "Asset Management",
        "Sector": "Financial Services",
        "30-Day Call IV": 46.04,
        "30-Day Put IV": null,
        "Market Cap": 3266248989
    },
    {
        "Ticker": "ENB",
        "Security Name": "Enbridge Inc",
        "Closing Price": 40.87,
        "Volume": 2465813,
        "360-Day Mean IV": 16.56,
        "Industry": "Oil & Gas Midstream",
        "Sector": "Energy",
        "30-Day Call IV": 24.52,
        "30-Day Put IV": null,
        "Market Cap": 86893329115
    },
    {
        "Ticker": "RY",
        "Security Name": "Royal Bank Of Canada",
        "Closing Price": 124.03,
        "Volume": 699219,
        "360-Day Mean IV": 16.81,
        "Industry": "Banks - Diversified",
        "Sector": "Financial Services",
        "30-Day Call IV": 18.95,
        "30-Day Put IV": 18.28,
        "Market Cap": 175211103530
    },
    {
        "Ticker": "JNJ",
        "Security Name": "Johnson & Johnson",
        "Closing Price": 161.6,
        "Volume": 4802680,
        "360-Day Mean IV": 16.88,
        "Industry": "Drug Manufacturers - General",
        "Sector": "Healthcare",
        "30-Day Call IV": 19.34,
        "30-Day Put IV": 16.0,
        "Market Cap": 389010576587
    },
    {
        "Ticker": "ET",
        "Security Name": "Energy Transfer LP",
        "Closing Price": 16.4,
        "Volume": 10771888,
        "360-Day Mean IV": 17.16,
        "Industry": "Oil & Gas Midstream",
        "Sector": "Energy",
        "30-Day Call IV": 12.52,
        "30-Day Put IV": 24.8,
        "Market Cap": 55268382415
    },
    {
        "Ticker": "PG",
        "Security Name": "Procter & Gamble Company (The)",
        "Closing Price": 169.3,
        "Volume": 5227425,
        "360-Day Mean IV": 17.22,
        "Industry": "Household & Personal Products",
        "Sector": "Consumer Defensive",
        "30-Day Call IV": 16.04,
        "30-Day Put IV": 15.58,
        "Market Cap": 398540832099
    },
    {
        "Ticker": "KO",
        "Security Name": "CocaCola Company (The)",
        "Closing Price": 66.67,
        "Volume": 9803315,
        "360-Day Mean IV": 17.42,
        "Industry": "Beverages - Non-Alcoholic",
        "Sector": "Consumer Defensive",
        "30-Day Call IV": 18.94,
        "30-Day Put IV": 15.27,
        "Market Cap": 287338909560
    },
    {
        "Ticker": "UL",
        "Security Name": "Unilever PLC",
        "Closing Price": 62.54,
        "Volume": 1680203,
        "360-Day Mean IV": 17.56,
        "Industry": "Household & Personal Products",
        "Sector": "Consumer Defensive",
        "30-Day Call IV": 16.59,
        "30-Day Put IV": 21.0,
        "Market Cap": 157694443518
    },
    {
        "Ticker": "DUK",
        "Security Name": "Duke Energy Corporation",
        "Closing Price": 117.06,
        "Volume": 2177078,
        "360-Day Mean IV": 17.67,
        "Industry": "Utilities - Regulated Electric",
        "Sector": "Utilities",
        "30-Day Call IV": 20.42,
        "30-Day Put IV": 24.06,
        "Market Cap": 90343233720
    },
    {
        "Ticker": "WCN",
        "Security Name": "Waste Connections, Inc.",
        "Closing Price": 176.91,
        "Volume": 604407,
        "360-Day Mean IV": 17.69,
        "Industry": "Waste Management",
        "Sector": "Industrials",
        "30-Day Call IV": 20.92,
        "30-Day Put IV": 18.77,
        "Market Cap": 45649400149
    },
    {
        "Ticker": "ORI",
        "Security Name": "Old Republic International Corporation",
        "Closing Price": 35.3,
        "Volume": 1393044,
        "360-Day Mean IV": 17.72,
        "Industry": "Insurance - Diversified",
        "Sector": "Financial Services",
        "30-Day Call IV": 16.46,
        "30-Day Put IV": null,
        "Market Cap": 9595707688
    },
    {
        "Ticker": "PEP",
        "Security Name": "PepsiCo, Inc.",
        "Closing Price": 169.84,
        "Volume": 4108524,
        "360-Day Mean IV": 18.02,
        "Industry": "Beverages - Non-Alcoholic",
        "Sector": "Consumer Defensive",
        "30-Day Call IV": 19.89,
        "30-Day Put IV": 14.45,
        "Market Cap": 233287536416
    },
    {
        "Ticker": "LNT",
        "Security Name": "Alliant Energy Corporation",
        "Closing Price": 61.14,
        "Volume": 1013726,
        "360-Day Mean IV": 18.15,
        "Industry": "Utilities - Regulated Electric",
        "Sector": "Utilities",
        "30-Day Call IV": 23.96,
        "30-Day Put IV": 34.24,
        "Market Cap": 15675014016
    },
    {
        "Ticker": "ED",
        "Security Name": "Consolidated Edison Inc",
        "Closing Price": 104.81,
        "Volume": 1203515,
        "360-Day Mean IV": 18.21,
        "Industry": "Utilities - Regulated Electric",
        "Sector": "Utilities",
        "30-Day Call IV": 21.88,
        "30-Day Put IV": 19.99,
        "Market Cap": 36246936059
    },
    {
        "Ticker": "PPL",
        "Security Name": "PPL Corporation",
        "Closing Price": 32.71,
        "Volume": 2706259,
        "360-Day Mean IV": 18.22,
        "Industry": "Utilities - Regulated Electric",
        "Sector": "Utilities",
        "30-Day Call IV": 20.73,
        "30-Day Put IV": 20.86,
        "Market Cap": 24131503497
    },
    {
        "Ticker": "FE",
        "Security Name": "FirstEnergy Corporation",
        "Closing Price": 43.68,
        "Volume": 2227990,
        "360-Day Mean IV": 18.26,
        "Industry": "Utilities - Regulated Electric",
        "Sector": "Utilities",
        "30-Day Call IV": 22.02,
        "30-Day Put IV": 20.16,
        "Market Cap": 25138559496
    },
    {
        "Ticker": "NI",
        "Security Name": "NiSource, Inc",
        "Closing Price": 35.14,
        "Volume": 2865215,
        "360-Day Mean IV": 18.46,
        "Industry": "Utilities - Regulated Gas",
        "Sector": "Utilities",
        "30-Day Call IV": 19.16,
        "30-Day Put IV": 24.86,
        "Market Cap": 15753449577
    },
    {
        "Ticker": "L",
        "Security Name": "Loews Corporation",
        "Closing Price": 80.62,
        "Volume": 565491,
        "360-Day Mean IV": 18.64,
        "Industry": "Insurance - Property & Casualty",
        "Sector": "Financial Services",
        "30-Day Call IV": 23.78,
        "30-Day Put IV": 24.77,
        "Market Cap": 17849772600
    },
    {
        "Ticker": "NWE",
        "Security Name": "NorthWestern Corporation",
        "Closing Price": 55.34,
        "Volume": 478347,
        "360-Day Mean IV": 18.67,
        "Industry": "Utilities - Diversified",
        "Sector": "Utilities",
        "30-Day Call IV": 33.52,
        "30-Day Put IV": 41.39,
        "Market Cap": 3391589265
    },
    {
        "Ticker": "ADC",
        "Security Name": "Agree Realty Corporation",
        "Closing Price": 74.45,
        "Volume": 1514858,
        "360-Day Mean IV": 18.7,
        "Industry": "REIT - Retail",
        "Sector": "Real Estate",
        "30-Day Call IV": 29.96,
        "30-Day Put IV": 19.21,
        "Market Cap": 7491497673
    },
    {
        "Ticker": "KMB",
        "Security Name": "Kimberly-Clark Corporation",
        "Closing Price": 135.62,
        "Volume": 1920329,
        "360-Day Mean IV": 18.72,
        "Industry": "Household & Personal Products",
        "Sector": "Consumer Defensive",
        "30-Day Call IV": 18.39,
        "30-Day Put IV": 15.71,
        "Market Cap": 45677416389
    },
    {
        "Ticker": "PNW",
        "Security Name": "Pinnacle West Capital Corporation",
        "Closing Price": 88.23,
        "Volume": 572547,
        "360-Day Mean IV": 18.78,
        "Industry": "Utilities - Regulated Electric",
        "Sector": "Utilities",
        "30-Day Call IV": 23.32,
        "30-Day Put IV": 21.48,
        "Market Cap": 10019300423
    },
    {
        "Ticker": "MMC",
        "Security Name": "Marsh & McLennan Companies, Inc.",
        "Closing Price": 221.84,
        "Volume": 997097,
        "360-Day Mean IV": 18.79,
        "Industry": "Insurance Brokers",
        "Sector": "Financial Services",
        "30-Day Call IV": 19.87,
        "30-Day Put IV": 20.02,
        "Market Cap": 109091130630
    },
    {
        "Ticker": "ETR",
        "Security Name": "Entergy Corporation",
        "Closing Price": 136.32,
        "Volume": 1355202,
        "360-Day Mean IV": 18.81,
        "Industry": "Utilities - Regulated Electric",
        "Sector": "Utilities",
        "30-Day Call IV": 24.5,
        "30-Day Put IV": 22.25,
        "Market Cap": 29109355115
    },
    {
        "Ticker": "DTE",
        "Security Name": "DTE Energy Company",
        "Closing Price": 126.63,
        "Volume": 939232,
        "360-Day Mean IV": 18.98,
        "Industry": "Utilities - Regulated Electric",
        "Sector": "Utilities",
        "30-Day Call IV": 21.57,
        "30-Day Put IV": 21.87,
        "Market Cap": 26214952730
    },
    {
        "Ticker": "AEE",
        "Security Name": "Ameren Corporation",
        "Closing Price": 88.12,
        "Volume": 691848,
        "360-Day Mean IV": 19.01,
        "Industry": "Utilities - Regulated Electric",
        "Sector": "Utilities",
        "30-Day Call IV": 22.18,
        "30-Day Put IV": 21.86,
        "Market Cap": 23498993356
    },
    {
        "Ticker": "SEIC",
        "Security Name": "SEI Investments Company",
        "Closing Price": 75.81,
        "Volume": 881519,
        "360-Day Mean IV": 19.13,
        "Industry": "Asset Management",
        "Sector": "Financial Services",
        "30-Day Call IV": 25.03,
        "30-Day Put IV": 34.92,
        "Market Cap": 9847179839
    },
    {
        "Ticker": "BRK.B",
        "Security Name": "Berkshire Hathaway Inc.",
        "Closing Price": 458.49,
        "Volume": 3162766,
        "360-Day Mean IV": 19.17,
        "Industry": "Insurance - Diversified",
        "Sector": "Financial Services",
        "30-Day Call IV": 20.19,
        "30-Day Put IV": 19.73,
        "Market Cap": 988890287655
    },
    {
        "Ticker": "GLPI",
        "Security Name": "Gaming and Leisure Properties, Inc.",
        "Closing Price": 50.49,
        "Volume": 1876310,
        "360-Day Mean IV": 19.17,
        "Industry": "REIT - Specialty",
        "Sector": "Real Estate",
        "30-Day Call IV": 20.79,
        "30-Day Put IV": null,
        "Market Cap": 13854025067
    },
    {
        "Ticker": "WEC",
        "Security Name": "WEC Energy Group, Inc.",
        "Closing Price": 97.0,
        "Volume": 1366695,
        "360-Day Mean IV": 19.18,
        "Industry": "Utilities - Regulated Electric",
        "Sector": "Utilities",
        "30-Day Call IV": 24.74,
        "30-Day Put IV": 22.56,
        "Market Cap": 30634790939
    },
    {
        "Ticker": "SRE",
        "Security Name": "Sempra Energy",
        "Closing Price": 85.17,
        "Volume": 1920936,
        "360-Day Mean IV": 19.21,
        "Industry": "Utilities - Diversified",
        "Sector": "Utilities",
        "30-Day Call IV": 25.03,
        "30-Day Put IV": 23.84,
        "Market Cap": 53899471931
    },
    {
        "Ticker": "SO",
        "Security Name": "Southern Company (The)",
        "Closing Price": 91.79,
        "Volume": 2762151,
        "360-Day Mean IV": 19.29,
        "Industry": "Utilities - Regulated Electric",
        "Sector": "Utilities",
        "30-Day Call IV": 22.31,
        "30-Day Put IV": 19.26,
        "Market Cap": 100365582728
    },
    {
        "Ticker": "PBA",
        "Security Name": "Pembina Pipeline Corp.",
        "Closing Price": 42.13,
        "Volume": 515850,
        "360-Day Mean IV": 19.38,
        "Industry": "Oil & Gas Midstream",
        "Sector": "Energy",
        "30-Day Call IV": 21.92,
        "30-Day Put IV": 30.69,
        "Market Cap": 23146082718
    },
    {
        "Ticker": "RSG",
        "Security Name": "Republic Services, Inc.",
        "Closing Price": 200.42,
        "Volume": 690787,
        "360-Day Mean IV": 19.42,
        "Industry": "Waste Management",
        "Sector": "Industrials",
        "30-Day Call IV": 25.45,
        "30-Day Put IV": 25.67,
        "Market Cap": 63118763432
    },
    {
        "Ticker": "GD",
        "Security Name": "General Dynamics Corporation",
        "Closing Price": 303.92,
        "Volume": 911499,
        "360-Day Mean IV": 19.43,
        "Industry": "Aerospace & Defense",
        "Sector": "Industrials",
        "30-Day Call IV": 18.56,
        "30-Day Put IV": 18.44,
        "Market Cap": 83510401809
    },
    {
        "Ticker": "CNP",
        "Security Name": "CenterPoint Energy, Inc.",
        "Closing Price": 29.75,
        "Volume": 4435836,
        "360-Day Mean IV": 19.49,
        "Industry": "Utilities - Regulated Electric",
        "Sector": "Utilities",
        "30-Day Call IV": 23.45,
        "30-Day Put IV": 22.49,
        "Market Cap": 19031793254
    },
    {
        "Ticker": "CNI",
        "Security Name": "Canadian National Railway Company",
        "Closing Price": 111.21,
        "Volume": 823861,
        "360-Day Mean IV": 19.56,
        "Industry": "Railroads",
        "Sector": "Industrials",
        "30-Day Call IV": 21.58,
        "30-Day Put IV": 20.82,
        "Market Cap": 70206873000
    },
    {
        "Ticker": "BNS",
        "Security Name": "Bank of Nova Scotia (The)",
        "Closing Price": 51.98,
        "Volume": 1100317,
        "360-Day Mean IV": 19.6,
        "Industry": "Banks - Diversified",
        "Sector": "Financial Services",
        "30-Day Call IV": 20.72,
        "30-Day Put IV": 29.93,
        "Market Cap": 63913027652
    },
    {
        "Ticker": "YUM",
        "Security Name": "Yum! Brands, Inc.",
        "Closing Price": 134.86,
        "Volume": 1312130,
        "360-Day Mean IV": 19.64,
        "Industry": "Restaurants",
        "Sector": "Consumer Cyclical",
        "30-Day Call IV": 24.77,
        "30-Day Put IV": 24.97,
        "Market Cap": 37980920110
    },
    {
        "Ticker": "LIN",
        "Security Name": "Linde PLC",
        "Closing Price": 476.0,
        "Volume": 1114048,
        "360-Day Mean IV": 19.67,
        "Industry": "Specialty Chemicals",
        "Sector": "Basic Materials",
        "30-Day Call IV": 22.48,
        "30-Day Put IV": 23.16,
        "Market Cap": 228801909756
    },
    {
        "Ticker": "XEL",
        "Security Name": "Xcel Energy Inc.",
        "Closing Price": 64.48,
        "Volume": 3465476,
        "360-Day Mean IV": 19.7,
        "Industry": "Utilities - Regulated Electric",
        "Sector": "Utilities",
        "30-Day Call IV": 23.34,
        "30-Day Put IV": 22.76,
        "Market Cap": 35827631026
    },
    {
        "Ticker": "EVRG",
        "Security Name": "Evergy Inc.",
        "Closing Price": 60.97,
        "Volume": 860902,
        "360-Day Mean IV": 19.75,
        "Industry": "Utilities - Regulated Electric",
        "Sector": "Utilities",
        "30-Day Call IV": 21.29,
        "30-Day Put IV": 20.15,
        "Market Cap": 14018778202
    },
    {
        "Ticker": "NVS",
        "Security Name": "Novartis AG",
        "Closing Price": 115.63,
        "Volume": 1542596,
        "360-Day Mean IV": 19.83,
        "Industry": "Drug Manufacturers - General",
        "Sector": "Healthcare",
        "30-Day Call IV": 23.96,
        "30-Day Put IV": 22.46,
        "Market Cap": 235931452000
    },
    {
        "Ticker": "ITW",
        "Security Name": "Illinois Tool Works Inc.",
        "Closing Price": 256.87,
        "Volume": 753002,
        "360-Day Mean IV": 19.86,
        "Industry": "Specialty Industrial Machinery",
        "Sector": "Industrials",
        "30-Day Call IV": 24.92,
        "30-Day Put IV": 24.44,
        "Market Cap": 76650008000
    },
    {
        "Ticker": "PKG",
        "Security Name": "Packaging Corporation of America",
        "Closing Price": 227.45,
        "Volume": 554402,
        "360-Day Mean IV": 19.94,
        "Industry": "Packaging & Containers",
        "Sector": "Consumer Cyclical",
        "30-Day Call IV": 21.08,
        "30-Day Put IV": 20.34,
        "Market Cap": 20424550323
    },
    {
        "Ticker": "EXC",
        "Security Name": "Exelon Corporation",
        "Closing Price": 40.23,
        "Volume": 4205947,
        "360-Day Mean IV": 19.95,
        "Industry": "Utilities - Regulated Electric",
        "Sector": "Utilities",
        "30-Day Call IV": 24.12,
        "30-Day Put IV": 21.09,
        "Market Cap": 40231010738
    },
    {
        "Ticker": "FYBR",
        "Security Name": "Frontier Communications Parent, Inc.",
        "Closing Price": 35.83,
        "Volume": 2373324,
        "360-Day Mean IV": 19.96,
        "Industry": "Telecom Services",
        "Sector": "Communication Services",
        "30-Day Call IV": 23.28,
        "30-Day Put IV": null,
        "Market Cap": 8905618160
    },
    {
        "Ticker": "AON",
        "Security Name": "Aon plc",
        "Closing Price": 371.71,
        "Volume": 995066,
        "360-Day Mean IV": 20.06,
        "Industry": "Insurance Brokers",
        "Sector": "Financial Services",
        "30-Day Call IV": 17.56,
        "30-Day Put IV": 17.58,
        "Market Cap": 80751083665
    },
    {
        "Ticker": "MO",
        "Security Name": "Altria Group, Inc.",
        "Closing Price": 50.25,
        "Volume": 5154036,
        "360-Day Mean IV": 20.08,
        "Industry": "Tobacco",
        "Sector": "Consumer Defensive",
        "30-Day Call IV": 21.01,
        "30-Day Put IV": 21.08,
        "Market Cap": 86310727806
    },
    {
        "Ticker": "EFC",
        "Security Name": "Ellington Financial Inc.",
        "Closing Price": 12.51,
        "Volume": 689189,
        "360-Day Mean IV": 20.08,
        "Industry": "REIT - Mortgage",
        "Sector": "Real Estate",
        "30-Day Call IV": 21.1,
        "30-Day Put IV": null,
        "Market Cap": 1063874331
    },
    {
        "Ticker": "O",
        "Security Name": "Realty Income Corporation",
        "Closing Price": 61.29,
        "Volume": 4239466,
        "360-Day Mean IV": 20.12,
        "Industry": "REIT - Retail",
        "Sector": "Real Estate",
        "30-Day Call IV": 23.19,
        "30-Day Put IV": 22.6,
        "Market Cap": 53369765182
    },
    {
        "Ticker": "EQR",
        "Security Name": "Equity Residential",
        "Closing Price": 75.01,
        "Volume": 1239217,
        "360-Day Mean IV": 20.2,
        "Industry": "REIT - Residential",
        "Sector": "Real Estate",
        "30-Day Call IV": 24.87,
        "30-Day Put IV": 24.72,
        "Market Cap": 28426689644
    },
    {
        "Ticker": "AEP",
        "Security Name": "American Electric Power Company, Inc.",
        "Closing Price": 99.11,
        "Volume": 2401024,
        "360-Day Mean IV": 20.24,
        "Industry": "Utilities - Regulated Electric",
        "Sector": "Utilities",
        "30-Day Call IV": 25.09,
        "30-Day Put IV": 24.37,
        "Market Cap": 52243037534
    },
    {
        "Ticker": "LMT",
        "Security Name": "Lockheed Martin Corporation",
        "Closing Price": 555.17,
        "Volume": 1264804,
        "360-Day Mean IV": 20.27,
        "Industry": "Aerospace & Defense",
        "Sector": "Industrials",
        "30-Day Call IV": 20.56,
        "30-Day Put IV": 16.85,
        "Market Cap": 132329212525
    },
    {
        "Ticker": "ICE",
        "Security Name": "Intercontinental Exchange Inc.",
        "Closing Price": 166.44,
        "Volume": 2429777,
        "360-Day Mean IV": 20.3,
        "Industry": "Financial Data & Stock Exchanges",
        "Sector": "Financial Services",
        "30-Day Call IV": 24.02,
        "30-Day Put IV": 23.69,
        "Market Cap": 95467417495
    },
    {
        "Ticker": "MDLZ",
        "Security Name": "Mondelez International, Inc.",
        "Closing Price": 69.54,
        "Volume": 4787697,
        "360-Day Mean IV": 20.39,
        "Industry": "Confectioners",
        "Sector": "Consumer Defensive",
        "30-Day Call IV": 23.28,
        "30-Day Put IV": 20.64,
        "Market Cap": 93278106111
    },
    {
        "Ticker": "MCD",
        "Security Name": "McDonald's Corporation",
        "Closing Price": 296.79,
        "Volume": 6530721,
        "360-Day Mean IV": 20.39,
        "Industry": "Restaurants",
        "Sector": "Consumer Cyclical",
        "30-Day Call IV": 24.56,
        "30-Day Put IV": 22.38,
        "Market Cap": 213891108684
    },
    {
        "Ticker": "TD",
        "Security Name": "Toronto Dominion Bank (The)",
        "Closing Price": 56.28,
        "Volume": 2617986,
        "360-Day Mean IV": 20.5,
        "Industry": "Banks - Diversified",
        "Sector": "Financial Services",
        "30-Day Call IV": 20.41,
        "30-Day Put IV": 20.78,
        "Market Cap": 102851700000
    },
    {
        "Ticker": "ADP",
        "Security Name": "Automatic Data Processing, Inc.",
        "Closing Price": 286.44,
        "Volume": 1300893,
        "360-Day Mean IV": 20.51,
        "Industry": "Staffing & Employment Services",
        "Sector": "Industrials",
        "30-Day Call IV": 23.4,
        "30-Day Put IV": 23.3,
        "Market Cap": 117237409138
    },
    {
        "Ticker": "AVB",
        "Security Name": "AvalonBay Communities, Inc.",
        "Closing Price": 228.8,
        "Volume": 646699,
        "360-Day Mean IV": 20.61,
        "Industry": "REIT - Residential",
        "Sector": "Real Estate",
        "30-Day Call IV": 25.36,
        "30-Day Put IV": 23.71,
        "Market Cap": 32532132318
    },
    {
        "Ticker": "APLE",
        "Security Name": "Apple Hospitality REIT, Inc.",
        "Closing Price": 15.1,
        "Volume": 1289934,
        "360-Day Mean IV": 20.63,
        "Industry": "REIT - Hotel & Motel",
        "Sector": "Real Estate",
        "30-Day Call IV": 21.54,
        "30-Day Put IV": 26.92,
        "Market Cap": 3659427438
    },
    {
        "Ticker": "ELS",
        "Security Name": "Equity Lifestyle Properties, Inc.",
        "Closing Price": 68.94,
        "Volume": 1290932,
        "360-Day Mean IV": 20.67,
        "Industry": "REIT - Residential",
        "Sector": "Real Estate",
        "30-Day Call IV": 28.2,
        "30-Day Put IV": 28.65,
        "Market Cap": 12857024657
    },
    {
        "Ticker": "BCE",
        "Security Name": "BCE, Inc.",
        "Closing Price": 32.69,
        "Volume": 1094432,
        "360-Day Mean IV": 20.76,
        "Industry": "Telecom Services",
        "Sector": "Communication Services",
        "30-Day Call IV": 24.13,
        "30-Day Put IV": 21.03,
        "Market Cap": 29823086999
    },
    {
        "Ticker": "COR",
        "Security Name": "Cencora, Inc.",
        "Closing Price": 233.57,
        "Volume": 821261,
        "360-Day Mean IV": 20.8,
        "Industry": "Medical Distribution",
        "Sector": "Healthcare",
        "30-Day Call IV": 28.21,
        "30-Day Put IV": 28.05,
        "Market Cap": 46585954823
    },
    {
        "Ticker": "MDT",
        "Security Name": "Medtronic PLC",
        "Closing Price": 90.6,
        "Volume": 3297879,
        "360-Day Mean IV": 20.83,
        "Industry": "Medical Devices",
        "Sector": "Healthcare",
        "30-Day Call IV": 23.93,
        "30-Day Put IV": 23.19,
        "Market Cap": 116173642339
    },
    {
        "Ticker": "EIX",
        "Security Name": "Edison International",
        "Closing Price": 84.48,
        "Volume": 1584798,
        "360-Day Mean IV": 20.86,
        "Industry": "Utilities - Regulated Electric",
        "Sector": "Utilities",
        "30-Day Call IV": 26.13,
        "30-Day Put IV": 25.64,
        "Market Cap": 32503938508
    },
    {
        "Ticker": "TRNO",
        "Security Name": "Terreno Realty Corporation",
        "Closing Price": 61.9,
        "Volume": 534490,
        "360-Day Mean IV": 20.87,
        "Industry": "REIT - Industrial",
        "Sector": "Real Estate",
        "30-Day Call IV": 42.15,
        "30-Day Put IV": 32.85,
        "Market Cap": 5985983913
    },
    {
        "Ticker": "CAG",
        "Security Name": "Conagra Brands",
        "Closing Price": 29.76,
        "Volume": 2424803,
        "360-Day Mean IV": 20.89,
        "Industry": "Packaged Foods",
        "Sector": "Consumer Defensive",
        "30-Day Call IV": 18.48,
        "30-Day Put IV": 16.33,
        "Market Cap": 14231492400
    },
    {
        "Ticker": "CL",
        "Security Name": "Colgate-Palmolive Company",
        "Closing Price": 95.74,
        "Volume": 4516232,
        "360-Day Mean IV": 20.93,
        "Industry": "Household & Personal Products",
        "Sector": "Consumer Defensive",
        "30-Day Call IV": 17.82,
        "30-Day Put IV": 18.51,
        "Market Cap": 78227923262
    },
    {
        "Ticker": "SON",
        "Security Name": "Sonoco Products Company",
        "Closing Price": 53.27,
        "Volume": 500658,
        "360-Day Mean IV": 20.96,
        "Industry": "Packaging & Containers",
        "Sector": "Consumer Cyclical",
        "30-Day Call IV": 28.59,
        "30-Day Put IV": 28.17,
        "Market Cap": 5234087478
    },
    {
        "Ticker": "HR",
        "Security Name": "Healthcare Realty Trust Incorporated",
        "Closing Price": 17.92,
        "Volume": 1893145,
        "360-Day Mean IV": 20.97,
        "Industry": "REIT - Healthcare Facilities",
        "Sector": "Real Estate",
        "30-Day Call IV": 36.45,
        "30-Day Put IV": null,
        "Market Cap": 6783510056
    },
    {
        "Ticker": "LHX",
        "Security Name": "L3Harris Technologies Inc",
        "Closing Price": 248.03,
        "Volume": 1032464,
        "360-Day Mean IV": 20.98,
        "Industry": "Aerospace & Defense",
        "Sector": "Industrials",
        "30-Day Call IV": 20.12,
        "30-Day Put IV": 20.94,
        "Market Cap": 47052578275
    },
    {
        "Ticker": "BKH",
        "Security Name": "Black Hills Corporation",
        "Closing Price": 60.35,
        "Volume": 292233,
        "360-Day Mean IV": 21.0,
        "Industry": "Utilities - Diversified",
        "Sector": "Utilities",
        "30-Day Call IV": 25.16,
        "30-Day Put IV": 20.45,
        "Market Cap": 4160125017
    },
    {
        "Ticker": "TU",
        "Security Name": "TELUS Corporation",
        "Closing Price": 16.14,
        "Volume": 2699310,
        "360-Day Mean IV": 21.04,
        "Industry": "Telecom Services",
        "Sector": "Communication Services",
        "30-Day Call IV": 46.35,
        "30-Day Put IV": 40.41,
        "Market Cap": 23822640000
    },
    {
        "Ticker": "AJG",
        "Security Name": "Arthur J. Gallagher & Co.",
        "Closing Price": 285.99,
        "Volume": 1007423,
        "360-Day Mean IV": 21.2,
        "Industry": "Insurance Brokers",
        "Sector": "Financial Services",
        "30-Day Call IV": 23.72,
        "30-Day Put IV": 23.85,
        "Market Cap": 62488815000
    },
    {
        "Ticker": "AWK",
        "Security Name": "American Water Works Company, Inc.",
        "Closing Price": 138.79,
        "Volume": 563875,
        "360-Day Mean IV": 21.2,
        "Industry": "Utilities - Regulated Water",
        "Sector": "Utilities",
        "30-Day Call IV": 25.11,
        "30-Day Put IV": 24.14,
        "Market Cap": 27039424073
    },
    {
        "Ticker": "VZ",
        "Security Name": "Verizon Communications Inc.",
        "Closing Price": 41.62,
        "Volume": 13506994,
        "360-Day Mean IV": 21.21,
        "Industry": "Telecom Services",
        "Sector": "Communication Services",
        "30-Day Call IV": 18.5,
        "30-Day Put IV": 20.63,
        "Market Cap": 175200222233
    },
    {
        "Ticker": "WM",
        "Security Name": "Waste Management, Inc.",
        "Closing Price": 208.26,
        "Volume": 1914893,
        "360-Day Mean IV": 21.22,
        "Industry": "Waste Management",
        "Sector": "Industrials",
        "30-Day Call IV": 29.91,
        "30-Day Put IV": 26.83,
        "Market Cap": 83529565989
    },
    {
        "Ticker": "DGX",
        "Security Name": "Quest Diagnostics Incorporated",
        "Closing Price": 155.92,
        "Volume": 507742,
        "360-Day Mean IV": 21.24,
        "Industry": "Diagnostics & Research",
        "Sector": "Healthcare",
        "30-Day Call IV": 19.72,
        "30-Day Put IV": 19.98,
        "Market Cap": 17356579071
    },
    {
        "Ticker": "BDX",
        "Security Name": "Becton, Dickinson and Company",
        "Closing Price": 238.91,
        "Volume": 919594,
        "360-Day Mean IV": 21.24,
        "Industry": "Medical Instruments & Supplies",
        "Sector": "Healthcare",
        "30-Day Call IV": 28.33,
        "30-Day Put IV": 27.78,
        "Market Cap": 69046533597
    },
    {
        "Ticker": "ES",
        "Security Name": "Eversource Energy",
        "Closing Price": 66.49,
        "Volume": 1553785,
        "360-Day Mean IV": 21.26,
        "Industry": "Utilities - Regulated Electric",
        "Sector": "Utilities",
        "30-Day Call IV": 26.47,
        "30-Day Put IV": 21.62,
        "Market Cap": 23421450774
    },
    {
        "Ticker": "SNA",
        "Security Name": "Snap-On Incorporated",
        "Closing Price": 332.59,
        "Volume": 378958,
        "360-Day Mean IV": 21.3,
        "Industry": "Tools & Accessories",
        "Sector": "Industrials",
        "30-Day Call IV": 20.37,
        "30-Day Put IV": 19.9,
        "Market Cap": 17521724891
    },
    {
        "Ticker": "SYY",
        "Security Name": "Sysco Corporation",
        "Closing Price": 75.1,
        "Volume": 3315611,
        "360-Day Mean IV": 21.3,
        "Industry": "Food Distribution",
        "Sector": "Consumer Defensive",
        "30-Day Call IV": 27.12,
        "30-Day Put IV": 27.04,
        "Market Cap": 37398484623
    },
    {
        "Ticker": "HON",
        "Security Name": "Honeywell International Inc.",
        "Closing Price": 206.1,
        "Volume": 6006657,
        "360-Day Mean IV": 21.35,
        "Industry": "Conglomerates",
        "Sector": "Industrials",
        "30-Day Call IV": 19.96,
        "30-Day Put IV": 20.75,
        "Market Cap": 133897234320
    },
    {
        "Ticker": "BNL",
        "Security Name": "Broadstone Net Lease, Inc.",
        "Closing Price": 18.05,
        "Volume": 929573,
        "360-Day Mean IV": 21.38,
        "Industry": "REIT - Diversified",
        "Sector": "Real Estate",
        "30-Day Call IV": 31.04,
        "30-Day Put IV": 31.2,
        "Market Cap": 3401161770
    },
    {
        "Ticker": "RPRX",
        "Security Name": "Royalty Pharma PLC",
        "Closing Price": 27.26,
        "Volume": 1960619,
        "360-Day Mean IV": 21.39,
        "Industry": "Biotechnology",
        "Sector": "Healthcare",
        "30-Day Call IV": 39.45,
        "30-Day Put IV": 35.18,
        "Market Cap": 16286140007
    },
    {
        "Ticker": "TTE",
        "Security Name": "TotalEnergies SE Sponsored ADR",
        "Closing Price": 64.7,
        "Volume": 1126165,
        "360-Day Mean IV": 21.4,
        "Industry": "Oil & Gas Integrated",
        "Sector": "Energy",
        "30-Day Call IV": 25.71,
        "30-Day Put IV": 29.09,
        "Market Cap": 154428966867
    },
    {
        "Ticker": "PAYX",
        "Security Name": "Paychex, Inc.",
        "Closing Price": 140.27,
        "Volume": 1493981,
        "360-Day Mean IV": 21.42,
        "Industry": "Staffing & Employment Services",
        "Sector": "Industrials",
        "30-Day Call IV": 21.4,
        "30-Day Put IV": 20.44,
        "Market Cap": 50515001805
    },
    {
        "Ticker": "PPG",
        "Security Name": "PPG Industries, Inc.",
        "Closing Price": 127.38,
        "Volume": 1255463,
        "360-Day Mean IV": 21.43,
        "Industry": "Specialty Chemicals",
        "Sector": "Basic Materials",
        "30-Day Call IV": 21.58,
        "30-Day Put IV": 21.49,
        "Market Cap": 29717754000
    },
    {
        "Ticker": "FAST",
        "Security Name": "Fastenal Company",
        "Closing Price": 76.67,
        "Volume": 1556956,
        "360-Day Mean IV": 21.43,
        "Industry": "Industrial Distribution",
        "Sector": "Industrials",
        "30-Day Call IV": 22.07,
        "30-Day Put IV": 21.03,
        "Market Cap": 43904776793
    },
    {
        "Ticker": "DTM",
        "Security Name": "DT Midstream, Inc.",
        "Closing Price": 87.42,
        "Volume": 634928,
        "360-Day Mean IV": 21.43,
        "Industry": "Oil & Gas Midstream",
        "Sector": "Energy",
        "30-Day Call IV": 25.96,
        "30-Day Put IV": 33.27,
        "Market Cap": 8489277522
    },
    {
        "Ticker": "CME",
        "Security Name": "CME Group Inc.",
        "Closing Price": 228.12,
        "Volume": 1079342,
        "360-Day Mean IV": 21.45,
        "Industry": "Financial Data & Stock Exchanges",
        "Sector": "Financial Services",
        "30-Day Call IV": 17.93,
        "30-Day Put IV": 18.46,
        "Market Cap": 82137690182
    },
    {
        "Ticker": "PM",
        "Security Name": "Philip Morris International Inc.",
        "Closing Price": 130.5,
        "Volume": 4503305,
        "360-Day Mean IV": 21.46,
        "Industry": "Tobacco",
        "Sector": "Consumer Defensive",
        "30-Day Call IV": 18.61,
        "30-Day Put IV": 18.47,
        "Market Cap": 202901600187
    },
    {
        "Ticker": "PEG",
        "Security Name": "Public Service Enterprise Group Incorporated",
        "Closing Price": 90.42,
        "Volume": 1557972,
        "360-Day Mean IV": 21.47,
        "Industry": "Utilities - Regulated Electric",
        "Sector": "Utilities",
        "30-Day Call IV": 27.41,
        "30-Day Put IV": 26.52,
        "Market Cap": 45036435826
    },
    {
        "Ticker": "IPG",
        "Security Name": "Interpublic Group of Companies, Inc. (The)",
        "Closing Price": 30.24,
        "Volume": 3083841,
        "360-Day Mean IV": 21.53,
        "Industry": "Advertising Agencies",
        "Sector": "Communication Services",
        "30-Day Call IV": 22.35,
        "30-Day Put IV": 21.6,
        "Market Cap": 11357858715
    },
    {
        "Ticker": "NOC",
        "Security Name": "Northrop Grumman Corporation",
        "Closing Price": 512.15,
        "Volume": 678583,
        "360-Day Mean IV": 21.59,
        "Industry": "Aerospace & Defense",
        "Sector": "Industrials",
        "30-Day Call IV": 21.34,
        "30-Day Put IV": 20.66,
        "Market Cap": 74899511957
    },
    {
        "Ticker": "ABT",
        "Security Name": "Abbott Laboratories",
        "Closing Price": 114.07,
        "Volume": 3985972,
        "360-Day Mean IV": 21.61,
        "Industry": "Medical Devices",
        "Sector": "Healthcare",
        "30-Day Call IV": 21.35,
        "30-Day Put IV": 21.54,
        "Market Cap": 198440022889
    },
    {
        "Ticker": "CM",
        "Security Name": "Canadian Imperial Bank of Commerce",
        "Closing Price": 63.3,
        "Volume": 640263,
        "360-Day Mean IV": 21.62,
        "Industry": "Banks - Diversified",
        "Sector": "Financial Services",
        "30-Day Call IV": 21.07,
        "30-Day Put IV": 22.67,
        "Market Cap": 59692026600
    },
    {
        "Ticker": "KHC",
        "Security Name": "Kraft Heinz Company",
        "Closing Price": 35.13,
        "Volume": 6950268,
        "360-Day Mean IV": 21.68,
        "Industry": "Packaged Foods",
        "Sector": "Consumer Defensive",
        "30-Day Call IV": 27.23,
        "30-Day Put IV": 24.45,
        "Market Cap": 42658295133
    },
    {
        "Ticker": "RTX",
        "Security Name": "RTX Corporation",
        "Closing Price": 125.43,
        "Volume": 4158291,
        "360-Day Mean IV": 21.71,
        "Industry": "Aerospace & Defense",
        "Sector": "Industrials",
        "30-Day Call IV": 18.82,
        "30-Day Put IV": 19.33,
        "Market Cap": 166851923677
    },
    {
        "Ticker": "V",
        "Security Name": "Visa Inc.",
        "Closing Price": 284.19,
        "Volume": 4289113,
        "360-Day Mean IV": 21.76,
        "Industry": "Credit Services",
        "Sector": "Financial Services",
        "30-Day Call IV": 23.84,
        "30-Day Put IV": 23.19,
        "Market Cap": 571222879820
    },
    {
        "Ticker": "MAA",
        "Security Name": "Mid-America Apartment Communities, Inc.",
        "Closing Price": 153.79,
        "Volume": 314067,
        "360-Day Mean IV": 21.8,
        "Industry": "REIT - Residential",
        "Sector": "Real Estate",
        "30-Day Call IV": 26.47,
        "30-Day Put IV": 25.26,
        "Market Cap": 17966671462
    }
]